[
  {
    "kanji": "悪い",
    "yomi": "わるい",
    "english": "bad",
    "romaji": "warui"
  },
  {
    "kanji": "安い",
    "yomi": "やすい",
    "english": "cheap",
    "romaji": "yasui"
  },
  {
    "kanji": "暗い",
    "yomi": "くらい",
    "english": "dark",
    "romaji": "kurai"
  },
  {
    "kanji": "医者",
    "yomi": "いしゃ",
    "english": "doctor",
    "romaji": "isha"
  },
  {
    "kanji": "委員",
    "yomi": "いいん",
    "english": "committee member",
    "romaji": "iin"
  },
  {
    "kanji": "意味",
    "yomi": "いみ",
    "english": "meaning",
    "romaji": "imi"
  },
  {
    "kanji": "育つ",
    "yomi": "そだつ",
    "english": "to grow",
    "romaji": "sodatsu"
  },
  {
    "kanji": "社員",
    "yomi": "しゃいん",
    "english": "company employee",
    "romaji": "shain"
  },
  {
    "kanji": "病院",
    "yomi": "びょういん",
    "english": "hospital",
    "romaji": "byouin"
  },
  {
    "kanji": "飲む",
    "yomi": "のむ",
    "english": "to drink",
    "romaji": "nomu"
  },
  {
    "kanji": "運ぶ",
    "yomi": "はこぶ",
    "english": "to carry",
    "romaji": "hakobu"
  },
  {
    "kanji": "泳ぐ",
    "yomi": "およぐ",
    "english": "to swim",
    "romaji": "oyogu"
  },
  {
    "kanji": "駅",
    "yomi": "えき",
    "english": "station",
    "romaji": "eki"
  },
  {
    "kanji": "中央",
    "yomi": "ちゅうおう",
    "english": "center",
    "romaji": "chuuou"
  },
  {
    "kanji": "横",
    "yomi": "よこ",
    "english": "side",
    "romaji": "yoko"
  },
  {
    "kanji": "屋",
    "yomi": "や",
    "english": "shop / roof",
    "romaji": "ya"
  },
  {
    "kanji": "温かい",
    "yomi": "あたたかい",
    "english": "warm",
    "romaji": "atatakai"
  },
  {
    "kanji": "化ける",
    "yomi": "ばける",
    "english": "to transform",
    "romaji": "bakeru"
  },
  {
    "kanji": "荷物",
    "yomi": "にもつ",
    "english": "luggage",
    "romaji": "nimotsu"
  },
  {
    "kanji": "世界",
    "yomi": "せかい",
    "english": "world",
    "romaji": "sekai"
  },
  {
    "kanji": "開く",
    "yomi": "あく / ひらく",
    "english": "to open",
    "romaji": "aku / hiraku"
  },
  {
    "kanji": "階",
    "yomi": "かい",
    "english": "floor",
    "romaji": "kai"
  },
  {
    "kanji": "寒い",
    "yomi": "さむい",
    "english": "cold",
    "romaji": "samui"
  },
  {
    "kanji": "感じる",
    "yomi": "かんじる",
    "english": "to feel",
    "romaji": "kanjiru"
  },
  {
    "kanji": "漢字",
    "yomi": "かんじ",
    "english": "kanji",
    "romaji": "kanji"
  },
  {
    "kanji": "図書館",
    "yomi": "としょかん",
    "english": "library",
    "romaji": "toshokan"
  },
  {
    "kanji": "岸",
    "yomi": "きし",
    "english": "shore",
    "romaji": "kishi"
  },
  {
    "kanji": "起きる",
    "yomi": "おきる",
    "english": "to wake up",
    "romaji": "okiru"
  },
  {
    "kanji": "期間",
    "yomi": "きかん",
    "english": "period",
    "romaji": "kikan"
  },
  {
    "kanji": "客",
    "yomi": "きゃく",
    "english": "guest",
    "romaji": "kyaku"
  },
  {
    "kanji": "研究",
    "yomi": "けんきゅう",
    "english": "research",
    "romaji": "kenkyuu"
  },
  {
    "kanji": "急ぐ",
    "yomi": "いそぐ",
    "english": "to hurry",
    "romaji": "isogu"
  },
  {
    "kanji": "級",
    "yomi": "きゅう",
    "english": "grade / level",
    "romaji": "kyuu"
  },
  {
    "kanji": "神宮",
    "yomi": "じんぐう",
    "english": "shrine",
    "romaji": "jinguu"
  },
  {
    "kanji": "野球",
    "yomi": "やきゅう",
    "english": "baseball",
    "romaji": "yakyuu"
  },
  {
    "kanji": "去る",
    "yomi": "さる",
    "english": "to leave",
    "romaji": "saru"
  },
  {
    "kanji": "橋",
    "yomi": "はし",
    "english": "bridge",
    "romaji": "hashi"
  },
  {
    "kanji": "授業",
    "yomi": "じゅぎょう",
    "english": "class",
    "romaji": "jugyou"
  },
  {
    "kanji": "曲",
    "yomi": "きょく",
    "english": "song / piece",
    "romaji": "kyoku"
  },
  {
    "kanji": "局",
    "yomi": "きょく",
    "english": "office / bureau",
    "romaji": "kyoku"
  },
  {
    "kanji": "銀行",
    "yomi": "ぎんこう",
    "english": "bank",
    "romaji": "ginkou"
  },
  {
    "kanji": "区",
    "yomi": "く",
    "english": "ward",
    "romaji": "ku"
  },
  {
    "kanji": "苦しい",
    "yomi": "くるしい",
    "english": "painful",
    "romaji": "kurushii"
  },
  {
    "kanji": "道具",
    "yomi": "どうぐ",
    "english": "tool",
    "romaji": "dougu"
  },
  {
    "kanji": "君",
    "yomi": "きみ",
    "english": "you",
    "romaji": "kimi"
  },
  {
    "kanji": "関係",
    "yomi": "かんけい",
    "english": "relationship",
    "romaji": "kankei"
  },
  {
    "kanji": "軽い",
    "yomi": "かるい",
    "english": "light",
    "romaji": "karui"
  },
  {
    "kanji": "血",
    "yomi": "ち",
    "english": "blood",
    "romaji": "chi"
  },
  {
    "kanji": "決める",
    "yomi": "きめる",
    "english": "to decide",
    "romaji": "kimeru"
  },
  {
    "kanji": "県",
    "yomi": "けん",
    "english": "prefecture",
    "romaji": "ken"
  },
  {
    "kanji": "冷蔵庫",
    "yomi": "れいぞうこ",
    "english": "refrigerator",
    "romaji": "reizouko"
  },
  {
    "kanji": "湖",
    "yomi": "みずうみ",
    "english": "lake",
    "romaji": "mizuumi"
  },
  {
    "kanji": "向く",
    "yomi": "むく",
    "english": "to face",
    "romaji": "muku"
  },
  {
    "kanji": "幸せ",
    "yomi": "しあわせ",
    "english": "happiness",
    "romaji": "shiawase"
  },
  {
    "kanji": "港",
    "yomi": "みなと",
    "english": "port",
    "romaji": "minato"
  },
  {
    "kanji": "番号",
    "yomi": "ばんごう",
    "english": "number",
    "romaji": "bangou"
  },
  {
    "kanji": "根",
    "yomi": "ね",
    "english": "root",
    "romaji": "ne"
  },
  {
    "kanji": "祭り",
    "yomi": "まつり",
    "english": "festival",
    "romaji": "matsuri"
  },
  {
    "kanji": "皿",
    "yomi": "さら",
    "english": "plate",
    "romaji": "sara"
  },
  {
    "kanji": "仕事",
    "yomi": "しごと",
    "english": "work",
    "romaji": "shigoto"
  },
  {
    "kanji": "死ぬ",
    "yomi": "しぬ",
    "english": "to die",
    "romaji": "shinu"
  },
  {
    "kanji": "使う",
    "yomi": "つかう",
    "english": "to use",
    "romaji": "tsukau"
  },
  {
    "kanji": "始める",
    "yomi": "はじめる",
    "english": "to start",
    "romaji": "hajimeru"
  },
  {
    "kanji": "指",
    "yomi": "ゆび",
    "english": "finger",
    "romaji": "yubi"
  },
  {
    "kanji": "歯",
    "yomi": "は",
    "english": "tooth",
    "romaji": "ha"
  },
  {
    "kanji": "詩",
    "yomi": "し",
    "english": "poem",
    "romaji": "shi"
  },
  {
    "kanji": "次",
    "yomi": "つぎ",
    "english": "next",
    "romaji": "tsugi"
  },
  {
    "kanji": "事",
    "yomi": "こと",
    "english": "thing",
    "romaji": "koto"
  },
  {
    "kanji": "持つ",
    "yomi": "もつ",
    "english": "to hold",
    "romaji": "motsu"
  },
  {
    "kanji": "式",
    "yomi": "しき",
    "english": "ceremony",
    "romaji": "shiki"
  },
  {
    "kanji": "実",
    "yomi": "み",
    "english": "fruit / truth",
    "romaji": "mi"
  },
  {
    "kanji": "写真",
    "yomi": "しゃしん",
    "english": "photo",
    "romaji": "shashin"
  },
  {
    "kanji": "者",
    "yomi": "もの",
    "english": "person",
    "romaji": "mono"
  },
  {
    "kanji": "主人",
    "yomi": "しゅじん",
    "english": "husband",
    "romaji": "shujin"
  },
  {
    "kanji": "守る",
    "yomi": "まもる",
    "english": "to protect",
    "romaji": "mamoru"
  },
  {
    "kanji": "取る",
    "yomi": "とる",
    "english": "to take",
    "romaji": "toru"
  },
  {
    "kanji": "酒",
    "yomi": "さけ",
    "english": "alcohol",
    "romaji": "sake"
  },
  {
    "kanji": "受ける",
    "yomi": "うける",
    "english": "to receive",
    "romaji": "ukeru"
  },
  {
    "kanji": "州",
    "yomi": "しゅう",
    "english": "state",
    "romaji": "shuu"
  },
  {
    "kanji": "拾う",
    "yomi": "ひろう",
    "english": "to pick up",
    "romaji": "hirou"
  },
  {
    "kanji": "終わる",
    "yomi": "おわる",
    "english": "to finish",
    "romaji": "owaru"
  },
  {
    "kanji": "習う",
    "yomi": "ならう",
    "english": "to learn",
    "romaji": "narau"
  },
  {
    "kanji": "集まる",
    "yomi": "あつまる",
    "english": "to gather",
    "romaji": "atsumaru"
  },
  {
    "kanji": "住む",
    "yomi": "すむ",
    "english": "to live",
    "romaji": "sumu"
  },
  {
    "kanji": "重い",
    "yomi": "おもい",
    "english": "heavy",
    "romaji": "omoi"
  },
  {
    "kanji": "宿",
    "yomi": "やど",
    "english": "inn",
    "romaji": "yado"
  },
  {
    "kanji": "場所",
    "yomi": "ばしょ",
    "english": "place",
    "romaji": "basho"
  },
  {
    "kanji": "暑い",
    "yomi": "あつい",
    "english": "hot",
    "romaji": "atsui"
  },
  {
    "kanji": "助ける",
    "yomi": "たすける",
    "english": "to help",
    "romaji": "tasukeru"
  },
  {
    "kanji": "昭和",
    "yomi": "しょうわ",
    "english": "Showa era",
    "romaji": "shouwa"
  },
  {
    "kanji": "消える",
    "yomi": "きえる",
    "english": "to disappear",
    "romaji": "kieru"
  },
  {
    "kanji": "商品",
    "yomi": "しょうひん",
    "english": "product",
    "romaji": "shouhin"
  },
  {
    "kanji": "文章",
    "yomi": "ぶんしょう",
    "english": "sentence",
    "romaji": "bunshou"
  },
  {
    "kanji": "勝つ",
    "yomi": "かつ",
    "english": "to win",
    "romaji": "katsu"
  },
  {
    "kanji": "乗る",
    "yomi": "のる",
    "english": "to ride",
    "romaji": "noru"
  },
  {
    "kanji": "植物",
    "yomi": "しょくぶつ",
    "english": "plant",
    "romaji": "shokubutsu"
  },
  {
    "kanji": "申す",
    "yomi": "もうす",
    "english": "to say (humble)",
    "romaji": "mousu"
  },
  {
    "kanji": "体",
    "yomi": "からだ",
    "english": "body",
    "romaji": "karada"
  },
  {
    "kanji": "神",
    "yomi": "かみ",
    "english": "god",
    "romaji": "kami"
  },
  {
    "kanji": "真",
    "yomi": "しん",
    "english": "truth",
    "romaji": "shin"
  },
  {
    "kanji": "深い",
    "yomi": "ふかい",
    "english": "deep",
    "romaji": "fukai"
  },
  {
    "kanji": "進む",
    "yomi": "すすむ",
    "english": "to go forward",
    "romaji": "susumu"
  },
  {
    "kanji": "整理",
    "yomi": "せいり",
    "english": "organize",
    "romaji": "seiri"
  },
  {
    "kanji": "昔",
    "yomi": "むかし",
    "english": "long ago",
    "romaji": "mukashi"
  },
  {
    "kanji": "全部",
    "yomi": "ぜんぶ",
    "english": "all",
    "romaji": "zenbu"
  },
  {
    "kanji": "相手",
    "yomi": "あいて",
    "english": "partner",
    "romaji": "aite"
  },
  {
    "kanji": "送る",
    "yomi": "おくる",
    "english": "to send",
    "romaji": "okuru"
  },
  {
    "kanji": "想う",
    "yomi": "おもう",
    "english": "to feel / think",
    "romaji": "omou"
  },
  {
    "kanji": "息",
    "yomi": "いき",
    "english": "breath",
    "romaji": "iki"
  },
  {
    "kanji": "速い",
    "yomi": "はやい",
    "english": "fast",
    "romaji": "hayai"
  },
  {
    "kanji": "家族",
    "yomi": "かぞく",
    "english": "family",
    "romaji": "kazoku"
  },
  {
    "kanji": "他",
    "yomi": "ほか",
    "english": "other",
    "romaji": "hoka"
  },
  {
    "kanji": "打つ",
    "yomi": "うつ",
    "english": "to hit",
    "romaji": "utsu"
  },
  {
    "kanji": "対する",
    "yomi": "たいする",
    "english": "to face / oppose",
    "romaji": "taisuru"
  },
  {
    "kanji": "待つ",
    "yomi": "まつ",
    "english": "to wait",
    "romaji": "matsu"
  },
  {
    "kanji": "代",
    "yomi": "だい",
    "english": "generation",
    "romaji": "dai"
  },
  {
    "kanji": "第一",
    "yomi": "だいいち",
    "english": "first",
    "romaji": "daiichi"
  },
  {
    "kanji": "問題",
    "yomi": "もんだい",
    "english": "problem",
    "romaji": "mondai"
  },
  {
    "kanji": "炭",
    "yomi": "すみ",
    "english": "charcoal",
    "romaji": "sumi"
  },
  {
    "kanji": "短い",
    "yomi": "みじかい",
    "english": "short",
    "romaji": "mijikai"
  },
  {
    "kanji": "談話",
    "yomi": "だんわ",
    "english": "talk",
    "romaji": "danwa"
  },
  {
    "kanji": "着る",
    "yomi": "きる",
    "english": "to wear",
    "romaji": "kiru"
  },
  {
    "kanji": "注意",
    "yomi": "ちゅうい",
    "english": "caution",
    "romaji": "chuui"
  },
  {
    "kanji": "柱",
    "yomi": "はしら",
    "english": "pillar",
    "romaji": "hashira"
  },
  {
    "kanji": "丁",
    "yomi": "ちょう",
    "english": "block / counter",
    "romaji": "chou"
  },
  {
    "kanji": "手帳",
    "yomi": "てちょう",
    "english": "notebook",
    "romaji": "techou"
  },
  {
    "kanji": "調べる",
    "yomi": "しらべる",
    "english": "to investigate",
    "romaji": "shiraberu"
  },
  {
    "kanji": "追う",
    "yomi": "おう",
    "english": "to chase",
    "romaji": "ou"
  },
  {
    "kanji": "定める",
    "yomi": "さだめる",
    "english": "to decide",
    "romaji": "sadameru"
  },
  {
    "kanji": "庭",
    "yomi": "にわ",
    "english": "garden",
    "romaji": "niwa"
  },
  {
    "kanji": "笛",
    "yomi": "ふえ",
    "english": "flute",
    "romaji": "fue"
  },
  {
    "kanji": "鉄",
    "yomi": "てつ",
    "english": "iron",
    "romaji": "tetsu"
  },
  {
    "kanji": "転ぶ",
    "yomi": "ころぶ",
    "english": "to fall",
    "romaji": "korobu"
  },
  {
    "kanji": "都会",
    "yomi": "とかい",
    "english": "city",
    "romaji": "tokai"
  },
  {
    "kanji": "度",
    "yomi": "ど",
    "english": "degree / time",
    "romaji": "do"
  },
  {
    "kanji": "投げる",
    "yomi": "なげる",
    "english": "to throw",
    "romaji": "nageru"
  },
  {
    "kanji": "豆",
    "yomi": "まめ",
    "english": "bean",
    "romaji": "mame"
  },
  {
    "kanji": "島",
    "yomi": "しま",
    "english": "island",
    "romaji": "shima"
  },
  {
    "kanji": "お湯",
    "yomi": "おゆ",
    "english": "hot water",
    "romaji": "oyu"
  },
  {
    "kanji": "登る",
    "yomi": "のぼる",
    "english": "to climb",
    "romaji": "noboru"
  },
  {
    "kanji": "等",
    "yomi": "など",
    "english": "etc.",
    "romaji": "nado"
  },
  {
    "kanji": "動く",
    "yomi": "うごく",
    "english": "to move",
    "romaji": "ugoku"
  },
  {
    "kanji": "子供",
    "yomi": "こども",
    "english": "child",
    "romaji": "kodomo"
  },
  {
    "kanji": "農業",
    "yomi": "のうぎょう",
    "english": "agriculture",
    "romaji": "nougyou"
  },
  {
    "kanji": "波",
    "yomi": "なみ",
    "english": "wave",
    "romaji": "nami"
  },
  {
    "kanji": "配る",
    "yomi": "くばる",
    "english": "to distribute",
    "romaji": "kubaru"
  },
  {
    "kanji": "倍",
    "yomi": "ばい",
    "english": "double",
    "romaji": "bai"
  },
  {
    "kanji": "箱",
    "yomi": "はこ",
    "english": "box",
    "romaji": "hako"
  },
  {
    "kanji": "畑",
    "yomi": "はたけ",
    "english": "field",
    "romaji": "hatake"
  },
  {
    "kanji": "発表",
    "yomi": "はっぴょう",
    "english": "presentation",
    "romaji": "happyou"
  },
  {
    "kanji": "反対",
    "yomi": "はんたい",
    "english": "opposite",
    "romaji": "hantai"
  },
  {
    "kanji": "坂",
    "yomi": "さか",
    "english": "slope",
    "romaji": "saka"
  },
  {
    "kanji": "板",
    "yomi": "いた",
    "english": "board",
    "romaji": "ita"
  },
  {
    "kanji": "皮",
    "yomi": "かわ",
    "english": "skin",
    "romaji": "kawa"
  },
  {
    "kanji": "悲しい",
    "yomi": "かなしい",
    "english": "sad",
    "romaji": "kanashii"
  },
  {
    "kanji": "美しい",
    "yomi": "うつくしい",
    "english": "beautiful",
    "romaji": "utsukushii"
  },
  {
    "kanji": "鼻",
    "yomi": "はな",
    "english": "nose",
    "romaji": "hana"
  },
  {
    "kanji": "筆",
    "yomi": "ふで",
    "english": "brush",
    "romaji": "fude"
  },
  {
    "kanji": "氷",
    "yomi": "こおり",
    "english": "ice",
    "romaji": "koori"
  },
  {
    "kanji": "表",
    "yomi": "おもて",
    "english": "front",
    "romaji": "omote"
  },
  {
    "kanji": "秒",
    "yomi": "びょう",
    "english": "second",
    "romaji": "byou"
  },
  {
    "kanji": "病気",
    "yomi": "びょうき",
    "english": "illness",
    "romaji": "byouki"
  },
  {
    "kanji": "負ける",
    "yomi": "まける",
    "english": "to lose",
    "romaji": "makeru"
  },
  {
    "kanji": "部分",
    "yomi": "ぶぶん",
    "english": "part",
    "romaji": "bubun"
  },
  {
    "kanji": "服",
    "yomi": "ふく",
    "english": "clothes",
    "romaji": "fuku"
  },
  {
    "kanji": "福",
    "yomi": "ふく",
    "english": "fortune",
    "romaji": "fuku"
  },
  {
    "kanji": "物",
    "yomi": "もの",
    "english": "thing",
    "romaji": "mono"
  },
  {
    "kanji": "平ら",
    "yomi": "たいら",
    "english": "flat",
    "romaji": "taira"
  },
  {
    "kanji": "返す",
    "yomi": "かえす",
    "english": "to return",
    "romaji": "kaesu"
  },
  {
    "kanji": "勉強",
    "yomi": "べんきょう",
    "english": "study",
    "romaji": "benkyou"
  },
  {
    "kanji": "放す",
    "yomi": "はなす",
    "english": "to release",
    "romaji": "hanasu"
  },
  {
    "kanji": "味",
    "yomi": "あじ",
    "english": "taste",
    "romaji": "aji"
  },
  {
    "kanji": "命",
    "yomi": "いのち",
    "english": "life",
    "romaji": "inochi"
  },
  {
    "kanji": "面",
    "yomi": "めん",
    "english": "face / surface",
    "romaji": "men"
  },
  {
    "kanji": "役",
    "yomi": "やく",
    "english": "role",
    "romaji": "yaku"
  },
  {
    "kanji": "薬",
    "yomi": "くすり",
    "english": "medicine",
    "romaji": "kusuri"
  },
  {
    "kanji": "理由",
    "yomi": "りゆう",
    "english": "reason",
    "romaji": "riyuu"
  },
  {
    "kanji": "油",
    "yomi": "あぶら",
    "english": "oil",
    "romaji": "abura"
  },
  {
    "kanji": "有名",
    "yomi": "ゆうめい",
    "english": "famous",
    "romaji": "yuumei"
  },
  {
    "kanji": "遊ぶ",
    "yomi": "あそぶ",
    "english": "to play",
    "romaji": "asobu"
  },
  {
    "kanji": "予定",
    "yomi": "よてい",
    "english": "plan",
    "romaji": "yotei"
  },
  {
    "kanji": "羊",
    "yomi": "ひつじ",
    "english": "sheep",
    "romaji": "hitsuji"
  },
  {
    "kanji": "洋服",
    "yomi": "ようふく",
    "english": "western clothes",
    "romaji": "youfuku"
  },
  {
    "kanji": "葉",
    "yomi": "は",
    "english": "leaf",
    "romaji": "ha"
  },
  {
    "kanji": "太陽",
    "yomi": "たいよう",
    "english": "sun",
    "romaji": "taiyou"
  },
  {
    "kanji": "様",
    "yomi": "さま",
    "english": "polite suffix",
    "romaji": "sama"
  },
  {
    "kanji": "落ちる",
    "yomi": "おちる",
    "english": "to fall",
    "romaji": "ochiru"
  },
  {
    "kanji": "流れる",
    "yomi": "ながれる",
    "english": "to flow",
    "romaji": "nagareru"
  },
  {
    "kanji": "旅行",
    "yomi": "りょこう",
    "english": "travel",
    "romaji": "ryokou"
  },
  {
    "kanji": "両方",
    "yomi": "りょうほう",
    "english": "both",
    "romaji": "ryouhou"
  },
  {
    "kanji": "緑",
    "yomi": "みどり",
    "english": "green",
    "romaji": "midori"
  },
  {
    "kanji": "礼",
    "yomi": "れい",
    "english": "thanks / bow",
    "romaji": "rei"
  },
  {
    "kanji": "列",
    "yomi": "れつ",
    "english": "line",
    "romaji": "retsu"
  },
  {
    "kanji": "練習",
    "yomi": "れんしゅう",
    "english": "practice",
    "romaji": "renshuu"
  },
  {
    "kanji": "道路",
    "yomi": "どうろ",
    "english": "road",
    "romaji": "douoro"
  },
  {
    "kanji": "和",
    "yomi": "わ",
    "english": "harmony / Japan",
    "romaji": "wa"
  },
  {
    "kanji": "列",
    "yomi": "れつ",
    "english": "line",
    "romaji": "retsu"
  },
  {
    "kanji": "練習",
    "yomi": "れんしゅう",
    "english": "practice",
    "romaji": "renshuu"
  },
  {
    "kanji": "道路",
    "yomi": "どうろ",
    "english": "road",
    "romaji": "douro"
  },
  {
    "kanji": "和",
    "yomi": "わ",
    "english": "peace",
    "romaji": "wa"
  }
]